README.md
setup.py
Wiki_requests/__init__.py
Wiki_requests.egg-info/PKG-INFO
Wiki_requests.egg-info/SOURCES.txt
Wiki_requests.egg-info/dependency_links.txt
Wiki_requests.egg-info/top_level.txt