Metadata-Version: 2.2
Name: Wiki_requests
Version: 0.0.1
Summary: A seemingly harmless package
Home-page: https://github.com/yourusername/your_package
Author: ZhangSan
Author-email: your@email.com
Classifier: Programming Language :: Python :: 3
Classifier: License :: OSI Approved :: MIT License
Classifier: Operating System :: OS Independent
Requires-Python: >=3.6
Dynamic: author
Dynamic: author-email
Dynamic: classifier
Dynamic: description
Dynamic: description-content-type
Dynamic: home-page
Dynamic: requires-python
Dynamic: summary
